log_arbor/.env
log_arbor/__init__.py
log_arbor/py.typed
log_arbor/utils.py
log_arbor-0.2.10.dist-info/WHEEL
log_arbor-0.2.10.dist-info/METADATA
log_arbor-0.2.10.dist-info/RECORD
