Metadata-Version: 2.4
Name: log-arbor
Version: 0.2.10
Summary: This is a library that is used in order to interact with LogArbor.
Author: Platon
Author-email: Platon <platon.tikhnenko@gmail.com>
License-Expression: MIT
Requires-Dist: datetime>=6.0
Requires-Dist: python-dotenv>=1.2.1
Requires-Dist: requests>=2.32.5
Requires-Python: >=3.14
